Workbook

Sheet Project Overview
A1: S.N | B1: Project Overview | C1: Description
A2: 1 | B2: Project Title | C2: Sales Performance Dashboard
A3: 2 | B3: Description | C3: Built a dynamic Sales Performance Dashboard using Microsoft Excel
C4: Transformed raw sales data into insights using pivot tables, charts, and KPI cards
C5: Tracked key metrics: sales, profit, units sold, trends, and individual contributions
C6: Delivered clear visibility into product and salesperson performance
C7: Demonstrated effective data-to-dashboard transformation for business reporting.
A8: 3 | B8: Key Excel Features Used | C8: Pivot Tables for summarizing sales, profit, region, product, and salesperson performance
C9: Pivot Charts (line, bar, pie) for visual storytelling
C10: SUM and basic formulas for KPI calculations
C11: Cell referencing to link pivot outputs with dashboard KPIs
C12: Structured sheets: Data Sheet, Functional Sheet, Dashboard Sheet.
A13: 4 | B13: Insights Generated | C13: Tablets and Laptops emerged as top-selling products
C14: February recorded the highest sales; January and June the lowest
C15: North region led in profit contribution
C16: Arjun ranked top in both sales and profit
C17: Dashboard enabled quick assessment of overall business performance.

Sheet Dashboard
A1: Sales Performance Dashboard
B2: Total Sales | E2: Total Profit | H2: Total Unit Sold | K2: Top Sales Person
B3: ='Functional Sheet'!B3 -> 119040 | E3: ='Functional Sheet'!B4 -> 31370 | H3: ='Functional Sheet'!B5 -> 21050 | K3: ='Functional Sheet'!A9 -> Arjun
H16: Salesperson Summary
H17: Salesperson | J17: Total Sales | L17: Total Profit
H18: ='Functional Sheet'!G13 -> Arjun | J18: =GETPIVOTDATA("Sum of Total Sales",'Functional Sheet'!$G$12,"Salesperson","Arjun") -> 19700 | L18: =GETPIVOTDATA("Total Profit",'Functional Sheet'!$G$12,"Salesperson","Arjun") -> 5550
H21: ='Functional Sheet'!G14 -> Nisha | J21: =GETPIVOTDATA("Sum of Total Sales",'Functional Sheet'!$G$12,"Salesperson","Nisha") -> 19450 | L21: =GETPIVOTDATA("Total Profit",'Functional Sheet'!$G$12,"Salesperson","Nisha") -> 5100
H24: ='Functional Sheet'!G15 -> Maya | J24: =GETPIVOTDATA("Sum of Total Sales",'Functional Sheet'!$G$12,"Salesperson","Maya") -> 17400 | L24: =GETPIVOTDATA("Total Profit",'Functional Sheet'!$G$12,"Salesperson","Maya") -> 4430

Sheet User Data
A1: Date | B1: Month-Year | C1: Region | D1: Salesperson | E1: Product | F1: Units Sold | G1: Unit Price | H1: Total Sales | I1: Cost per Unit | J1: Profit
A2: 45727 | B2: =TEXT(Table1[[#This Row],[Date]], "mmm") -> Mar | C2: South | D2: Arjun | E2: Tablet | F2: 5 | G2: 500 | H2: 2500 | I2: 350 | J2: 750
A3: 45813 | B3: =TEXT(Table1[[#This Row],[Date]], "mmm") -> Jun | C3: East | D3: Maya | E3: Tablet | F3: 1 | G3: 500 | H3: 500 | I3: 350 | J3: 150
A4: 45705 | B4: =TEXT(Table1[[#This Row],[Date]], "mmm") -> Feb | C4: South | D4: Arjun | E4: Phone | F4: 2 | G4: 400 | H4: 800 | I4: 300 | J4: 200
A5: 45689 | B5: =TEXT(Table1[[#This Row],[Date]], "mmm") -> Feb | C5: East | D5: Puja | E5: Headphones | F5: 9 | G5: 120 | H5: 1080 | I5: 80 | J5: 360
A6: 45721 | B6: =TEXT(Table1[[#This Row],[Date]], "mmm") -> Mar | C6: North | D6: Sita | E6: Headphones | F6: 7 | G6: 120 | H6: 840 | I6: 80 | J6: 280
A7: 45786 | B7: =TEXT(Table1[[#This Row],[Date]], "mmm") -> May | C7: West | D7: Kiran | E7: Phone | F7: 7 | G7: 400 | H7: 2800 | I7: 300 | J7: 700
A8: 45731 | B8: =TEXT(Table1[[#This Row],[Date]], "mmm") -> Mar | C8: South | D8: Sita | E8: Smartwatch | F8: 1 | G8: 250 | H8: 250 | I8: 180 | J8: 70
A9: 45798 | B9: =TEXT(Table1[[#This Row],[Date]], "mmm") -> May | C9: North | D9: Puja | E9: Phone | F9: 3 | G9: 400 | H9: 1200 | I9: 300 | J9: 300
A10: 45697 | B10: =TEXT(Table1[[#This Row],[Date]], "mmm") -> Feb | C10: North | D10: Anish | E10: Laptop | F10: 8 | G10: 700 | H10: 5600 | I10: 550 | J10: 1200
A11: 45710 | B11: =TEXT(Table1[[#This Row],[Date]], "mmm") -> Feb | C11: South | D11: Nisha | E11: Tablet | F11: 10 | G11: 500 | H11: 5000 | I11: 350 | J11: 1500
A12: 45811 | B12: =TEXT(Table1[[#This Row],[Date]], "mmm") -> Jun | C12: West | D12: Puja | E12: Phone | F12: 4 | G12: 400 | H12: 1600 | I12: 300 | J12: 400
A13: 45691 | B13: =TEXT(Table1[[#This Row],[Date]], "mmm") -> Feb | C13: North | D13: Sita | E13: Tablet | F13: 1 | G13: 500 | H13: 500 | I13: 350 | J13: 150
... A51: 45795 | B51: =TEXT(Table1[[#This Row],[Date]], "mmm") -> May | C51: South | D51: Ravi | E51: Smartwatch | F51: 2 | G51: 250 | H51: 500 | I51: 180 | J51: 140

Sheet Functional Sheet
A1: CALCULATIONS | D1: RESION-WISE PROFIT | G1: Monthly Sales Trend
A2: Title | B2: Total Value | D2: Resion | E2: Sum of Profit | G2: Month | H2: Sales
A3: Sales | B3: =SUM(Table1[Total Sales]) -> 119040 | D3: East | E3: 8120 | G3: Jan | H3: 14320
A4: Profit | B4: =SUM(Table1[Profit]) -> 31370 | D4: North | E4: 10560 | G4: Feb | H4: 37380
A5: Units Sold | B5: =SUM(Table1[Unit Price]) -> 21050 | D5: South | E5: 5470 | G5: Mar | H5: 24140
D6: West | E6: 7220 | G6: Apr | H6: 14700
A7: TOP SALES PERSON | D7: Grand Total | E7: 31370 | G7: May | H7: 18200
A8: Sales Person | B8: Total Sells | G8: Jun | H8: 10300
A9: Arjun | B9: 19700 | D9: PRODUCT-WISE SALES | G9: Grand Total | H9: 119040
A10: Nisha | B10: 19450 | D10: Products | E10: Sales
A11: Maya | B11: 17400 | D11: Headphones | E11: 4440 | G11: SALESPERSON SUMMARY
A12: Kiran | B12: 13610 | D12: Laptop | E12: 34300 | G12: Salesperson | H12: Sum of Total Sales | I12: Total Profit
A13: Anish | B13: 13050 | D13: Phone | E13: 24800 | G13: Arjun | H13: 19700 | I13: 5550
A14: Puja | B14: 12840 | D14: Smartwatch | E14: 15500 | G14: Nisha | H14: 19450 | I14: 5100
A15: Sita | B15: 12590 | D15: Tablet | E15: 40000 | G15: Maya | H15: 17400 | I15: 4430
A16: Ravi | B16: 10400 | D16: Grand Total | E16: 119040 | G16: Kiran | H16: 13610 | I16: 3540
A17: Grand Total | B17: 119040 | G17: Anish | H17: 13050 | I17: 3040
G18: Puja | H18: 12840 | I18: 3580
G19: Sita | H19: 12590 | I19: 3160
G20: Ravi | H20: 10400 | I20: 2970
G21: Grand Total | H21: 119040 | I21: 31370
